[{"id": 5, "name": "colon", "contours": [[[59, 70], [59, 69], [60, 68], [60, 67], [61, 67], [62, 67], [63, 67], [64, 68], [64, 69], [65, 70], [64, 71], [64, 72], [63, 73], [62, 73], [61, 74], [60, 73], [59, 72], [59, 71]]]}, {"id": 8, "name": "femur_left", "contours": [[[82, 56], [82, 55], [83, 54], [83, 53], [83, 52], [85, 51], [88, 49], [89, 48], [91, 49], [92, 50], [101, 57], [102, 58], [105, 58], [106, 59], [107, 60], [107, 63], [107, 68], [106, 69], [106, 70], [106, 71], [103, 72], [98, 65], [99, 67], [101, 72], [98, 66], [100, 73], [95, 63], [93, 63], [90, 63], [88, 63], [87, 62], [85, 61]]]}, {"id": 9, "name": "femur_right", "contours": [[[15, 56], [17, 55], [18, 54], [21, 55], [23, 54], [25, 53], [29, 51], [31, 49], [33, 48], [35, 48], [38, 49], [40, 50], [41, 52], [42, 57], [42, 58], [42, 59], [37, 62], [33, 63], [31, 62], [29, 61], [27, 60], [22, 68], [23, 66], [19, 68], [17, 67], [25, 60], [21, 63], [15, 65], [15, 64], [20, 61], [14, 62], [23, 59]]]}, {"id": 11, "name": "gluteus_maximus_left", "contours": [[[70, 80], [71, 79], [73, 79], [76, 79], [78, 79], [81, 78], [84, 78], [87, 77], [90, 76], [91, 75], [93, 75], [96, 75], [98, 75], [101, 75], [103, 75], [105, 76], [104, 79], [102, 80], [98, 81], [95, 82], [91, 83], [89, 83], [87, 84], [84, 84], [81, 85], [82, 84], [78, 85], [75, 85], [73, 85], [70, 85], [67, 82], [68, 81]]]}, {"id": 12, "name": "gluteus_maximus_right", "contours": [[[16, 77], [9, 73], [11, 67], [13, 68], [15, 69], [17, 70], [19, 71], [23, 71], [25, 72], [28, 72], [33, 74], [34, 75], [35, 76], [37, 77], [43, 79], [49, 80], [46, 80], [52, 81], [56, 83], [56, 84], [56, 85], [55, 86], [51, 86], [46, 85], [38, 83], [36, 82], [33, 82], [30, 81], [27, 80], [25, 79], [22, 79], [21, 78]]]}, {"id": 17, "name": "hip_left", "contours": [[[72, 48], [73, 49], [71, 46], [71, 45], [79, 55], [72, 42], [77, 51], [73, 43], [75, 44], [81, 46], [81, 52], [81, 53], [82, 47], [82, 50], [81, 56], [85, 49], [81, 57], [90, 65], [88, 64], [90, 66], [85, 62], [86, 63], [83, 61], [82, 60], [86, 70], [84, 74], [81, 74], [80, 69], [80, 68], [79, 73], [79, 72], [79, 59]]]}, {"id": 18, "name": "hip_right", "contours": [[[39, 49], [43, 57], [40, 47], [41, 50], [42, 53], [43, 54], [44, 46], [47, 45], [51, 43], [47, 51], [45, 55], [53, 43], [53, 44], [49, 50], [53, 45], [53, 47], [45, 59], [44, 63], [44, 66], [44, 67], [44, 70], [44, 71], [44, 74], [41, 74], [39, 73], [37, 69], [41, 61], [43, 58], [39, 62], [36, 63], [33, 65], [34, 64]]]}, {"id": 19, "name": "iliac_artery_left", "contours": [[[86, 39], [86, 38], [87, 38], [88, 38], [88, 39], [88, 40], [87, 41], [86, 40]]]}, {"id": 20, "name": "iliac_artery_right", "contours": [[[36, 38], [36, 37], [37, 37], [38, 37], [39, 38], [39, 39], [38, 39], [37, 39], [36, 39]]]}, {"id": 21, "name": "iliac_vena_left", "contours": [[[81, 40], [82, 39], [83, 38], [84, 38], [85, 39], [85, 40], [85, 41], [84, 42], [83, 42], [82, 42], [81, 41]]]}, {"id": 22, "name": "iliac_vena_right", "contours": [[[40, 39], [40, 38], [41, 38], [42, 38], [43, 39], [43, 40], [43, 41], [42, 42], [41, 42], [40, 41], [39, 40]]]}, {"id": 23, "name": "iliopsoas_left", "contours": [[[90, 44], [90, 43], [91, 42], [91, 41], [92, 41], [93, 40], [94, 40], [95, 41], [96, 41], [97, 42], [97, 43], [97, 44], [97, 45], [98, 46], [98, 47], [98, 48], [97, 48], [96, 48], [95, 48], [94, 47], [93, 47], [92, 47], [91, 47], [90, 46], [90, 45]]]}, {"id": 24, "name": "iliopsoas_right", "contours": [[[27, 42], [27, 41], [28, 40], [29, 39], [30, 39], [31, 39], [32, 39], [33, 40], [34, 40], [35, 41], [35, 42], [35, 43], [34, 44], [33, 45], [32, 45], [31, 45], [30, 45], [29, 46], [28, 46], [27, 46], [27, 45], [27, 44], [27, 43]]]}, {"id": 53, "name": "urinary_bladder", "contours": [[[54, 47], [54, 46], [54, 45], [53, 38], [54, 37], [56, 37], [58, 36], [60, 36], [62, 36], [65, 37], [68, 37], [70, 39], [70, 40], [71, 41], [70, 42], [70, 43], [71, 48], [72, 49], [73, 50], [72, 54], [72, 55], [71, 56], [69, 58], [67, 59], [64, 59], [62, 59], [59, 59], [57, 59], [55, 59], [52, 58], [50, 53], [50, 52]]]}]