[{"id": 1, "name": "adrenal_gland_right", "contours": [[[45, 10], [40, 8], [41, 8], [40, 7], [42, 8], [41, 7], [44, 9], [43, 8], [42, 6], [43, 6], [44, 7], [44, 6], [45, 8], [46, 9], [47, 10], [48, 11], [49, 12], [50, 13], [51, 14], [51, 15], [51, 16], [50, 15], [49, 14], [48, 13], [47, 12], [46, 11]]]}, {"id": 4, "name": "autochthon_right", "contours": [[[16, 34], [15, 29], [14, 24], [14, 19], [13, 14], [13, 9], [13, 4], [13, 0], [18, 0], [22, 1], [22, 6], [24, 11], [24, 16], [26, 21], [28, 26], [29, 31], [31, 36], [32, 41], [31, 46], [33, 51], [30, 56], [26, 61], [19, 68], [16, 73], [16, 66], [15, 71], [16, 64], [17, 54], [16, 59], [17, 49], [17, 44], [17, 39]]]}, {"id": 5, "name": "colon", "contours": [[[69, 31], [68, 30], [67, 29], [67, 28], [68, 27], [68, 26], [70, 26], [73, 25], [77, 20], [79, 20], [81, 20], [82, 21], [82, 22], [82, 23], [82, 24], [84, 31], [83, 32], [84, 35], [84, 36], [84, 37], [83, 38], [83, 39], [83, 40], [81, 46], [79, 47], [76, 46], [75, 45], [74, 44], [74, 43], [74, 42], [74, 34], [73, 33]], [[62, 77], [63, 75], [63, 74], [64, 73], [64, 72], [66, 71], [67, 71], [68, 71], [70, 71], [71, 71], [72, 72], [73, 72], [75, 73], [76, 75], [76, 76], [76, 77], [76, 78], [76, 79], [75, 80], [74, 82], [73, 84], [72, 85], [71, 86], [69, 86], [68, 86], [66, 86], [65, 86], [63, 84], [62, 83], [61, 82], [61, 81], [62, 79]], [[40, 79], [40, 78], [41, 77], [42, 77], [43, 77], [44, 78], [44, 79], [44, 80], [43, 81], [43, 82], [42, 82], [41, 82], [40, 82], [40, 81], [39, 80]]]}, {"id": 7, "name": "duodenum", "contours": [[[56, 25], [56, 21], [56, 20], [56, 19], [57, 18], [59, 17], [60, 16], [61, 16], [63, 16], [65, 16], [68, 17], [70, 18], [66, 22], [63, 24], [68, 21], [65, 23], [70, 21], [62, 25], [61, 31], [61, 32], [61, 33], [61, 34], [61, 35], [60, 36], [60, 30], [59, 37], [60, 29], [58, 38], [60, 28], [56, 38], [60, 27], [60, 26]]]}, {"id": 12, "name": "gluteus_maximus_right", "contours": [[[14, 100], [14, 99], [13, 96], [13, 95], [13, 94], [13, 93], [12, 90], [12, 89], [12, 88], [13, 87], [16, 92], [16, 91], [16, 90], [17, 96], [17, 97], [18, 98], [19, 102], [20, 103], [20, 104], [21, 108], [21, 109], [21, 110], [21, 111], [19, 111], [17, 111], [15, 111], [14, 108], [14, 107], [14, 106], [14, 105], [14, 102], [14, 101]]]}, {"id": 18, "name": "hip_right", "contours": [[[50, 104], [51, 103], [52, 103], [53, 102], [54, 102], [55, 102], [56, 102], [57, 103], [57, 104], [58, 105], [58, 106], [58, 107], [57, 107], [56, 107], [55, 107], [54, 107], [53, 107], [52, 107], [51, 107], [50, 106], [50, 105]]]}, {"id": 20, "name": "iliac_artery_right", "contours": [[[46, 72], [47, 71], [48, 71], [48, 72], [48, 73], [47, 74], [46, 75], [45, 75], [44, 74], [45, 73]]]}, {"id": 22, "name": "iliac_vena_right", "contours": [[[41, 67], [42, 66], [42, 65], [43, 64], [44, 63], [45, 63], [46, 64], [46, 65], [46, 66], [46, 67], [46, 68], [46, 69], [45, 70], [45, 71], [45, 72], [44, 73], [43, 72], [42, 71], [41, 70], [41, 69], [41, 68]]]}, {"id": 24, "name": "iliopsoas_right", "contours": [[[38, 40], [37, 37], [36, 34], [35, 31], [34, 28], [34, 25], [33, 21], [33, 20], [36, 22], [38, 23], [41, 26], [43, 29], [45, 32], [46, 35], [48, 38], [48, 41], [49, 44], [50, 47], [49, 50], [49, 53], [50, 56], [50, 59], [49, 63], [49, 64], [46, 62], [44, 61], [42, 58], [41, 55], [40, 52], [39, 49], [38, 46], [38, 43]]]}, {"id": 25, "name": "inferior_vena_cava", "contours": [[[52, 18], [53, 17], [54, 17], [54, 18], [54, 19], [54, 20], [53, 19], [52, 19]]]}, {"id": 27, "name": "kidney_right", "contours": [[[37, 17], [37, 16], [38, 15], [38, 14], [38, 13], [39, 13], [40, 13], [41, 14], [42, 14], [42, 15], [43, 16], [44, 17], [44, 18], [44, 19], [44, 20], [44, 21], [43, 22], [42, 22], [41, 22], [40, 22], [39, 21], [39, 20], [38, 19], [38, 18]]]}, {"id": 28, "name": "liver", "contours": [[[43, 5], [58, 6], [61, 6], [44, 0], [47, 0], [51, 0], [55, 0], [59, 0], [62, 0], [66, 0], [70, 0], [74, 0], [77, 0], [79, 1], [80, 3], [81, 6], [73, 9], [83, 12], [75, 10], [78, 11], [65, 7], [81, 13], [76, 14], [75, 17], [71, 17], [65, 8], [68, 16], [55, 13], [55, 12], [55, 11], [49, 10], [47, 9]]]}, {"id": 30, "name": "lung_lower_lobe_right", "contours": [[[25, 2], [25, 1], [24, 0], [25, 0], [26, 0], [27, 0], [28, 0], [29, 0], [30, 0], [31, 0], [32, 0], [33, 0], [34, 0], [36, 0], [37, 0], [38, 0], [39, 0], [40, 0], [37, 1], [38, 1], [36, 2], [35, 3], [34, 4], [33, 5], [32, 6], [31, 7], [30, 8], [28, 8], [27, 7], [27, 6], [26, 5], [26, 4]]]}, {"id": 33, "name": "portal_vein_and_splenic_vein", "contours": [[[56, 9], [57, 8], [58, 7], [59, 7], [60, 7], [61, 7], [62, 7], [62, 8], [61, 9], [60, 10], [60, 11], [59, 12], [58, 12], [57, 12], [56, 11], [56, 10]]]}, {"id": 43, "name": "rib_right_12", "contours": [[[24, 6], [24, 5], [25, 6], [25, 7], [24, 7]]]}, {"id": 47, "name": "sacrum", "contours": [[[17, 73], [19, 70], [22, 69], [24, 68], [28, 62], [30, 62], [31, 63], [32, 64], [34, 65], [35, 66], [35, 67], [35, 70], [35, 71], [35, 73], [28, 74], [30, 74], [33, 74], [27, 75], [24, 76], [17, 89], [17, 87], [17, 86], [17, 85], [20, 79], [15, 84], [15, 83], [22, 76], [15, 82], [15, 81], [16, 79], [16, 78], [16, 77]]]}, {"id": 48, "name": "small_bowel", "contours": [[[67, 58], [68, 57], [69, 57], [70, 57], [70, 58], [70, 59], [70, 60], [69, 61], [68, 61], [67, 61], [67, 60], [67, 59]], [[54, 70], [54, 69], [56, 67], [57, 66], [58, 65], [59, 65], [60, 63], [60, 64], [62, 62], [63, 62], [64, 62], [66, 62], [66, 63], [66, 66], [66, 67], [66, 68], [64, 70], [64, 71], [63, 73], [62, 74], [62, 76], [61, 77], [60, 80], [58, 80], [57, 80], [56, 79], [55, 79], [54, 78], [54, 76], [54, 75], [54, 73], [54, 72]]]}, {"id": 52, "name": "urinary_bladder", "contours": [[[37, 93], [38, 92], [43, 87], [46, 86], [47, 85], [52, 84], [54, 83], [55, 82], [57, 82], [60, 83], [62, 85], [64, 86], [66, 87], [68, 88], [69, 89], [70, 90], [69, 94], [69, 95], [68, 98], [67, 99], [66, 101], [65, 102], [63, 102], [62, 103], [59, 103], [54, 101], [52, 102], [49, 104], [46, 103], [42, 102], [40, 101], [38, 97]]]}, {"id": 54, "name": "vertebrae_L2", "contours": [[[29, 24], [30, 24], [30, 25], [30, 26], [29, 26], [29, 25]]]}, {"id": 55, "name": "vertebrae_L3", "contours": [[[33, 35], [33, 34], [34, 35], [35, 36], [35, 37], [34, 37], [33, 37], [33, 36]]]}, {"id": 56, "name": "vertebrae_L4", "contours": [[[36, 48], [36, 47], [37, 48], [37, 49], [36, 50], [36, 49]]]}, {"id": 57, "name": "vertebrae_L5", "contours": [[[32, 58], [32, 57], [32, 56], [32, 55], [33, 55], [34, 56], [35, 57], [36, 57], [37, 57], [38, 58], [38, 59], [38, 60], [38, 61], [37, 61], [36, 61], [35, 60], [34, 60], [33, 59]]]}]